owa/env/desktop/__init__.py
owa/env/desktop/constants.py
owa/env/desktop/keyboard_mouse/__init__.py
owa/env/desktop/keyboard_mouse/callables.py
owa/env/desktop/keyboard_mouse/listeners.py
owa/env/desktop/keyboard_mouse/raw_input.py
owa/env/desktop/screen/__init__.py
owa/env/desktop/screen/callables.py
owa/env/desktop/utils/__init__.py
owa/env/desktop/utils/from_vk.py
owa/env/desktop/utils/to_vk.py
owa/env/desktop/utils/windows_utils.py
owa/env/desktop/window/__init__.py
owa/env/desktop/window/callables.py
owa/env/desktop/window/listeners.py
owa/env/plugins/desktop.py
owa_env_desktop-0.6.5.dist-info/METADATA
owa_env_desktop-0.6.5.dist-info/WHEEL
owa_env_desktop-0.6.5.dist-info/entry_points.txt
owa_env_desktop-0.6.5.dist-info/RECORD
