Metadata-Version: 2.4
Name: owa-env-desktop
Version: 0.6.5
Summary: Desktop environment plugin for Open World Agents with mouse, keyboard, and window control
License: MIT
Requires-Python: >=3.11
Requires-Dist: bettercam; sys_platform == 'win32'
Requires-Dist: evdev<1.9.2; sys_platform == 'linux'
Requires-Dist: loguru
Requires-Dist: numpy>=2.0
Requires-Dist: owa-core==0.6.5
Requires-Dist: owa-msgs==0.6.5
Requires-Dist: pygetwindow; sys_platform == 'win32'
Requires-Dist: pynput>=1.8.0
Requires-Dist: pyobjc-framework-applicationservices>=10.1; sys_platform == 'darwin'
Requires-Dist: pyobjc-framework-quartz>=10.1; sys_platform == 'darwin'
Requires-Dist: pywin32>=307; sys_platform == 'win32'
